{
  "layers": {
    "apoli:above_overlay": {
      "displacement": {
        "x": 0,
        "y": 0
      },
      "direction": {
        "x": "NONE",
        "y": "NONE"
      },
      "sync": "apoli:above_overlay"
    },
    "apoli:bottom_overlay": {
      "displacement": {
        "x": 0,
        "y": 0
      },
      "direction": {
        "x": "NONE",
        "y": "NONE"
      },
      "sync": "apoli:bottom_overlay"
    },
    "apoli:overlay": {
      "displacement": {
        "x": 0,
        "y": 0
      },
      "direction": {
        "x": "NONE",
        "y": "NONE"
      },
      "sync": "apoli:overlay"
    },
    "artifacts:artifact_cooldowns": {
      "displacement": {
        "x": 0,
        "y": 0
      },
      "direction": {
        "x": "NONE",
        "y": "NONE"
      },
      "sync": "artifacts:artifact_cooldowns"
    },
    "artifacts:helium_flamingo_charge": {
      "displacement": {
        "x": 0,
        "y": 0
      },
      "direction": {
        "x": "NONE",
        "y": "NONE"
      },
      "sync": "artifacts:helium_flamingo_charge"
    },
    "cold_sweat:body_temp": {
      "displacement": {
        "x": 0,
        "y": 0
      },
      "direction": {
        "x": "NONE",
        "y": "NONE"
      },
      "sync": "cold_sweat:body_temp"
    },
    "cold_sweat:vague_temp": {
      "displacement": {
        "x": 0,
        "y": 0
      },
      "direction": {
        "x": "NONE",
        "y": "NONE"
      },
      "sync": "cold_sweat:vague_temp"
    },
    "cold_sweat:world_temp": {
      "displacement": {
        "x": 0,
        "y": 0
      },
      "direction": {
        "x": "NONE",
        "y": "NONE"
      },
      "sync": "cold_sweat:world_temp"
    },
    "create:blueprint": {
      "displacement": {
        "x": 0,
        "y": 0
      },
      "direction": {
        "x": "NONE",
        "y": "NONE"
      },
      "sync": "create:blueprint"
    },
    "create:goggle_info": {
      "displacement": {
        "x": 0,
        "y": 0
      },
      "direction": {
        "x": "NONE",
        "y": "NONE"
      },
      "sync": "create:goggle_info"
    },
    "create:linked_controller": {
      "displacement": {
        "x": 0,
        "y": 0
      },
      "direction": {
        "x": "NONE",
        "y": "NONE"
      },
      "sync": "create:linked_controller"
    },
    "create:remaining_air": {
      "displacement": {
        "x": 0,
        "y": 0
      },
      "direction": {
        "x": "NONE",
        "y": "NONE"
      },
      "sync": "create:remaining_air"
    },
    "create:schematic": {
      "displacement": {
        "x": 0,
        "y": 0
      },
      "direction": {
        "x": "NONE",
        "y": "NONE"
      },
      "sync": "create:schematic"
    },
    "create:toolbox": {
      "displacement": {
        "x": 0,
        "y": 0
      },
      "direction": {
        "x": "NONE",
        "y": "NONE"
      },
      "sync": "create:toolbox"
    },
    "create:track_placement": {
      "displacement": {
        "x": 0,
        "y": 0
      },
      "direction": {
        "x": "NONE",
        "y": "NONE"
      },
      "sync": "create:track_placement"
    },
    "create:train_hud": {
      "displacement": {
        "x": 0,
        "y": 0
      },
      "direction": {
        "x": "NONE",
        "y": "NONE"
      },
      "sync": "create:train_hud"
    },
    "create:value_settings": {
      "displacement": {
        "x": 0,
        "y": 0
      },
      "direction": {
        "x": "NONE",
        "y": "NONE"
      },
      "sync": "create:value_settings"
    },
    "createpropulsion:assembly_gauge": {
      "displacement": {
        "x": 0,
        "y": 0
      },
      "direction": {
        "x": "NONE",
        "y": "NONE"
      },
      "sync": "createpropulsion:assembly_gauge"
    },
    "dungeonsdelight:ravenous_rush_vignette": {
      "displacement": {
        "x": 0,
        "y": 0
      },
      "direction": {
        "x": "NONE",
        "y": "NONE"
      },
      "sync": "dungeonsdelight:ravenous_rush_vignette"
    },
    "dungeonsdelight:voracity_overlay": {
      "displacement": {
        "x": 0,
        "y": 0
      },
      "direction": {
        "x": "NONE",
        "y": "NONE"
      },
      "sync": "dungeonsdelight:voracity_overlay"
    },
    "eidolon:hearts": {
      "displacement": {
        "x": 0,
        "y": 0
      },
      "direction": {
        "x": "NONE",
        "y": "NONE"
      },
      "sync": "eidolon:hearts"
    },
    "eidolon:mana_bar": {
      "displacement": {
        "x": 0,
        "y": 0
      },
      "direction": {
        "x": "NONE",
        "y": "NONE"
      },
      "sync": "eidolon:mana_bar"
    },
    "eidolon:raven_charge": {
      "displacement": {
        "x": 0,
        "y": 0
      },
      "direction": {
        "x": "NONE",
        "y": "NONE"
      },
      "sync": "eidolon:raven_charge"
    },
    "immersive_aircraft:ia_overlay": {
      "displacement": {
        "x": 0,
        "y": 0
      },
      "direction": {
        "x": "NONE",
        "y": "NONE"
      },
      "sync": "immersive_aircraft:ia_overlay"
    },
    "map_atlases:atlas": {
      "displacement": {
        "x": 0,
        "y": 0
      },
      "direction": {
        "x": "NONE",
        "y": "NONE"
      },
      "sync": "map_atlases:atlas"
    },
    "mindful_eating:mindful_eating_hunger": {
      "displacement": {
        "x": 0,
        "y": 0
      },
      "direction": {
        "x": "NONE",
        "y": "NONE"
      },
      "sync": "mindful_eating:mindful_eating_hunger"
    },
    "minecraft:bossbar": {
      "displacement": {
        "x": 0,
        "y": 0
      },
      "direction": {
        "x": "NONE",
        "y": "DOWN"
      },
      "sync": "minecraft:bossbar"
    },
    "minecraft:chat": {
      "displacement": {
        "x": 0,
        "y": 0
      },
      "direction": {
        "x": "NONE",
        "y": "UP"
      },
      "sync": "minecraft:chat"
    },
    "minecraft:effects": {
      "displacement": {
        "x": 0,
        "y": 0
      },
      "direction": {
        "x": "LEFT",
        "y": "DOWN"
      },
      "sync": "minecraft:effects"
    },
    "minecraft:hotbar": {
      "displacement": {
        "x": 2,
        "y": 0
      },
      "direction": {
        "x": "NONE",
        "y": "UP"
      },
      "sync": "minecraft:hotbar"
    },
    "minecraft:other": {
      "displacement": {
        "x": 0,
        "y": 0
      },
      "direction": {
        "x": "NONE",
        "y": "NONE"
      },
      "sync": "minecraft:other"
    },
    "minecraft:players": {
      "displacement": {
        "x": 0,
        "y": 0
      },
      "direction": {
        "x": "NONE",
        "y": "DOWN"
      },
      "sync": "minecraft:players"
    },
    "minecraft:sidebar": {
      "displacement": {
        "x": 0,
        "y": 0
      },
      "direction": {
        "x": "LEFT",
        "y": "NONE"
      },
      "sync": "minecraft:sidebar"
    },
    "minecraft:subtitles": {
      "displacement": {
        "x": 0,
        "y": 0
      },
      "direction": {
        "x": "LEFT",
        "y": "UP"
      },
      "sync": "minecraft:subtitles"
    },
    "minecraft:toasts": {
      "displacement": {
        "x": 0,
        "y": 0
      },
      "direction": {
        "x": "LEFT",
        "y": "DOWN"
      },
      "sync": "minecraft:toasts"
    },
    "netherexp:agitated": {
      "displacement": {
        "x": 0,
        "y": 0
      },
      "direction": {
        "x": "NONE",
        "y": "NONE"
      },
      "sync": "netherexp:agitated"
    },
    "oreganized:stunning": {
      "displacement": {
        "x": 0,
        "y": 0
      },
      "direction": {
        "x": "NONE",
        "y": "NONE"
      },
      "sync": "oreganized:stunning"
    },
    "patchouli:book_right_click": {
      "displacement": {
        "x": 0,
        "y": 0
      },
      "direction": {
        "x": "NONE",
        "y": "NONE"
      },
      "sync": "patchouli:book_right_click"
    },
    "patchouli:multiblock_progress": {
      "displacement": {
        "x": 0,
        "y": 0
      },
      "direction": {
        "x": "NONE",
        "y": "NONE"
      },
      "sync": "patchouli:multiblock_progress"
    },
    "rubinated_nether:ruby_lens_overlay": {
      "displacement": {
        "x": 0,
        "y": 0
      },
      "direction": {
        "x": "NONE",
        "y": "NONE"
      },
      "sync": "rubinated_nether:ruby_lens_overlay"
    },
    "scannable:scanner_results": {
      "displacement": {
        "x": 0,
        "y": 0
      },
      "direction": {
        "x": "NONE",
        "y": "NONE"
      },
      "sync": "scannable:scanner_results"
    },
    "sleep_tight:sleep_indicator": {
      "displacement": {
        "x": 0,
        "y": 0
      },
      "direction": {
        "x": "NONE",
        "y": "NONE"
      },
      "sync": "sleep_tight:sleep_indicator"
    },
    "structure_gel:building_tool_overlay": {
      "displacement": {
        "x": 0,
        "y": 0
      },
      "direction": {
        "x": "NONE",
        "y": "NONE"
      },
      "sync": "structure_gel:building_tool_overlay"
    },
    "supplementaries:cannon_charge_overlay": {
      "displacement": {
        "x": 0,
        "y": 0
      },
      "direction": {
        "x": "NONE",
        "y": "NONE"
      },
      "sync": "supplementaries:cannon_charge_overlay"
    },
    "supplementaries:quiver_overlay": {
      "displacement": {
        "x": 0,
        "y": 0
      },
      "direction": {
        "x": "NONE",
        "y": "NONE"
      },
      "sync": "supplementaries:quiver_overlay"
    },
    "supplementaries:slimed_overlay": {
      "displacement": {
        "x": 0,
        "y": 0
      },
      "direction": {
        "x": "NONE",
        "y": "NONE"
      },
      "sync": "supplementaries:slimed_overlay"
    },
    "twilightforest:quest_ram_indicator": {
      "displacement": {
        "x": 0,
        "y": 0
      },
      "direction": {
        "x": "NONE",
        "y": "NONE"
      },
      "sync": "twilightforest:quest_ram_indicator"
    },
    "undergarden:brittleness_armor": {
      "displacement": {
        "x": 0,
        "y": 0
      },
      "direction": {
        "x": "NONE",
        "y": "NONE"
      },
      "sync": "undergarden:brittleness_armor"
    },
    "undergarden:dweller_xp_bar": {
      "displacement": {
        "x": 0,
        "y": 0
      },
      "direction": {
        "x": "NONE",
        "y": "NONE"
      },
      "sync": "undergarden:dweller_xp_bar"
    },
    "undergarden:undergarden_portal_overlay": {
      "displacement": {
        "x": 0,
        "y": 0
      },
      "direction": {
        "x": "NONE",
        "y": "NONE"
      },
      "sync": "undergarden:undergarden_portal_overlay"
    },
    "undergarden:virulence_hearts": {
      "displacement": {
        "x": 0,
        "y": 0
      },
      "direction": {
        "x": "NONE",
        "y": "NONE"
      },
      "sync": "undergarden:virulence_hearts"
    },
    "vs_clockwork:gravitron": {
      "displacement": {
        "x": 0,
        "y": 0
      },
      "direction": {
        "x": "NONE",
        "y": "NONE"
      },
      "sync": "vs_clockwork:gravitron"
    },
    "yungscavebiomes:buffeted": {
      "displacement": {
        "x": 0,
        "y": 0
      },
      "direction": {
        "x": "NONE",
        "y": "NONE"
      },
      "sync": "yungscavebiomes:buffeted"
    },
    "zetter:painting_info": {
      "displacement": {
        "x": 0,
        "y": 0
      },
      "direction": {
        "x": "NONE",
        "y": "NONE"
      },
      "sync": "zetter:painting_info"
    },
    "zettergallery:painting_info": {
      "displacement": {
        "x": 0,
        "y": 0
      },
      "direction": {
        "x": "NONE",
        "y": "NONE"
      },
      "sync": "zettergallery:painting_info"
    }
  }
}